mpackview/__init__.py
mpackview/main.py
mpackview/mpacklog.ui
mpackview/plot_callback.py
mpackview/plot_item.py
mpackview/plot_widget.py
mpackview/sized_tree_widget.py
mpackview/stream_client.py
mpackview/window.py
mpackview-3.1.0.dist-info/entry_points.txt
mpackview-3.1.0.dist-info/WHEEL
mpackview-3.1.0.dist-info/METADATA
mpackview-3.1.0.dist-info/RECORD
